twofas_cli/__init__.py
twofas_cli/common.py
twofas_cli/crypt.py
twofas_cli/twofas_cli.py
twofas_cli/api/__init__.py
twofas_cli/api/api.py
twofas_cli-0.1.0.dist-info/LICENSE
twofas_cli-0.1.0.dist-info/METADATA
twofas_cli-0.1.0.dist-info/WHEEL
twofas_cli-0.1.0.dist-info/entry_points.txt
twofas_cli-0.1.0.dist-info/top_level.txt
twofas_cli-0.1.0.dist-info/RECORD
