Metadata-Version: 2.1
Name: twofas-cli
Version: 0.1.0
Summary: Unofficial CLI tool for 2FAS using the browser extension api
Home-page: https://packages.python.org/twofas-cli
Author: dspd
Author-email: inmost-chimps-0j@icloud.com
License: BSD
Keywords: 2fas twofas
Classifier: Development Status :: 4 - Beta
Classifier: Topic :: Utilities
Classifier: License :: OSI Approved :: BSD License
Requires-Python: >=3.7
License-File: LICENSE
Requires-Dist: Click
Requires-Dist: requests
Requires-Dist: cryptography
Requires-Dist: pyqrcode
Requires-Dist: pypng
Requires-Dist: websockets
